hm_hardware_defs/__init__.py
hm_hardware_defs/variant.py
hm_hardware_defs-0.1.5.dist-info/LICENSE
hm_hardware_defs-0.1.5.dist-info/METADATA
hm_hardware_defs-0.1.5.dist-info/WHEEL
hm_hardware_defs-0.1.5.dist-info/top_level.txt
hm_hardware_defs-0.1.5.dist-info/RECORD
