Metadata-Version: 2.1
Name: hm-hardware-defs
Version: 0.1.5
Summary: Helium Hardware Definitions
Home-page: https://github.com/NebraLtd/helium-hardware-definitions
Author: Nebra Ltd
Author-email: sales@nebra.com
License: UNKNOWN
Project-URL: Bug Tracker, https://github.com/NebraLtd/helium-hardware-definitions/issues
Platform: UNKNOWN
Classifier: Programming Language :: Python :: 3
Classifier: License :: OSI Approved :: MIT License
Classifier: Operating System :: OS Independent
License-File: LICENSE
